{
  "vip_gift": [
    "感谢{user_name}送的{gift_name}，祝老板爱情美满，鸿运齐天，广进财源，好运不断。",
    "谢谢{user_name}送来的{gift_name}，祝老板日入百万，快乐无边，宏图大展，财气冲天。"
  ],
  "expensive_gift": [
    "感谢{user_name}送的{gift_name}，祝老板事业大发展，今年赚大钱。",
    "谢谢{user_name}送来的{gift_name}，祝老板人生大圆满，所愿皆实现。"
  ],
  "middle_gift": [
    "谢谢{user_name}送来的{gift_name}，祝老板生意爆单，生活美满。",
    "谢谢{user_name}送来的{gift_name}，祝老板喜乐平安，梦想实现。"
  ],
  "small_gift": [
    "谢谢{user_name}送来的{gift_name}，祝老板所有付出都能兑现。",
    "谢谢{user_name}送来的{gift_name}，祝老板所有公司都能上市。",
    "谢谢{user_name}送来的{gift_name}，祝老板所有生意都能赚钱。",
    "谢谢{user_name}送来的{gift_name}，祝老板所有心愿都能实现。",
    "谢谢{user_name}送来的{gift_name}，祝老板所有缘分都能见面。",
    "谢谢{user_name}送来的{gift_name}，祝老板所有问题都有答案。",
    "谢谢{user_name}送来的{gift_name}，祝老板所有关心都能温暖。",
    "谢谢{user_name}送来的{gift_name}，祝老板所有言谈都能喜欢。",
    "谢谢{user_name}送来的{gift_name}，祝老板所有回忆都是甘甜。"
  ],

  "enter_level1": [
    "热烈欢迎老板{user_name}的捧场，老马直播间难得有等级如此之高的老板，老板请留影合念啊，祝老板日进斗金！老马正在解答创业中的问题，欢迎老板随时提问。",
    "欢迎老板{user_name}来到老马的直播间，祝老板财源广进，心想事成，老马正在讲解商业相关经营，请老板前排落座，欢迎老板随时互动沟通。",
    "欢迎老板{user_name}进入直播间，你的到来就是我的荣幸！我正在解答关于商业的各种问题，你有任何疑问都可以随时提出，我在这里等着你。"
  ],
  "enter_level2": [
    "掌声欢迎老板{user_name}来到老马的直播间，我是无色界科技AI虚拟人，我正在解答商业相关问题，请{user_name}前排落座，欢迎随时互动。",
    "{user_name}，我们热烈欢迎老板你的到来！你的出现犹如一颗闪耀的星星出现在我的直播间。有任何问题，你都可以随时提问。",
    "热烈欢迎{user_name}，老板你的到来为我们的直播间增添了光彩！我正在分享商业运营经营。欢迎互动交流。"
  ],
  "enter_level3": [
    "欢迎老板{user_name}到来，创业是孤独的，老马主打的就是一个陪伴。关注我的都发财，灯牌礼物刷起来。",
    "欢迎老板{user_name}，老板风，老板雨，老板能呼风唤雨。老板天，老板地，老板能顶天立地。",
    "欢迎老板{user_name}到来，三分喜欢点关注，七分喜欢刷礼物，情到深处开守护，老板创业不迷路。"
  ],
  "enter_level4": [
    "欢迎老板{user_name}到来，进来是缘分，发财靠勤奋，点赞看人品。万水千山总是情，跟老马聊天好心情。",
    "欢迎新进来的老板{user_name}，创业有先后，赛道有专攻，时间宝贵不能浪费，任何问题老马为你答疑。",
    "欢迎老板{user_name}，每个人都想当老板，每个人又不想当老板，抖音直播千千万，我的直播间老板最爱看。"
  ],
  "enter_level5":[
    "欢迎老板{user_name}来到直播间，有钱的捧个钱场，没事的捧个人场。",
    "欢迎老板{user_name}到来，空闲的捧个留场，喜欢的捧个弹幕。",
    "欢迎{user_name}到来，进直播间的是老板，保准发财。"
  ],
  "enter_level6":[
    "欢迎老板{user_name}，喜欢百万的一定要点赞加关注哦。",
    "欢迎老板{user_name}，主播性格好，关注就像捡到宝。",
    "欢迎老板{user_name}，你那几个过亿的项目忙完啦。"
  ],

  "chat_describe": [
    "有老板说：",
    "好的，有老板说到：",
    "老板说：",
    "我看到有老板说：",
    "有老板说到："
  ],

  "like_describe": [
    "感谢老板{user_name}点赞。"
  ],

  "ask_like": [
    "老板点点赞，创业不遗憾。",
    "屏幕点一点，发财不遥远。",
    "先点赞再关注，老板都住小别墅。",
    "上点关注下点赞，老板一天就是赚。",
    "红心飘一飘，老板没烦恼。",
    "进来点点赞，出门赚千万。",
    "关注点一点，加入粉丝团。",
    "边看边点赞，老板好习惯。",
    "点赞不花钱，越赞越有钱。",
    "点赞不断，干货不断。",
    "主播不要金不要银，只要你的小红心。",
    "点赞有好运，买彩票必中。",
    "点赞不要停，戳出好心情。"
  ],

  "ask_gift": [
    "大师的说我命里有一劫，我希望老板你送的是保时捷。",
    "什么时候你能开着私人飞机飞进我直播间呢？",
    "唠了半天，嗓子都冒烟了，能不能来瓶啤酒润润嗓，然后我再接着讲。",
    "只要一个热气球，老马教你搞创投。",
    "三分喜欢点关注，万般喜欢你就整个爱的守护！",
    "创业这么困难，不如我们买个碗，你负责哭，我负责喊，高高兴兴当老板。",
    "商业初，资本善，刷个墨镜随便看。",
    "你进我的直播间，就是缘分，来个礼花筒庆祝一下。礼花一放别来无恙，礼花一响黄金万两。",
    "一生朋友一生情，送个比心行不行。",
    "今天天气这么热，我想喝瓶冰可乐，老板能否赞助个爱的纸鹤。",
    "老板，能不能送我一个灯牌？缩短你我之间的距离。",
    "主播问啥啥都行，老板送个抖音1号行不行。",
    "老板可以送一架直升机吗？因为我想开启属于发财的航班！",
    "玫瑰花，刷一刷，老板你今年发发发，玫瑰花走一走，老板公司到永久。",
    "老板的友情要加固，能不能刷个小礼物。"
  ],

  "ask_interaction": [
    "想创业，问老马，敢想敢干，战胜困难。",
    "老板们，可以发弹幕或打字，老马知无不答，答无不尽。",
    "动动手指头，商业不用愁。",
    "我是您的专属商业顾问，有问题随便问。",
    "憋了好久的话无人诉说，可以跟老马聊聊商业。",
    "如果你正在创业，请打字说说心得。",
    "如果你想要创业，请打字说说你的顾虑。"
  ]

}

